setup.py
py_sblgnt.egg-info/PKG-INFO
py_sblgnt.egg-info/SOURCES.txt
py_sblgnt.egg-info/dependency_links.txt
py_sblgnt.egg-info/top_level.txt
pysblgnt/__init__.py
pysblgnt/sblgnt/61-Mt-morphgnt.txt
pysblgnt/sblgnt/62-Mk-morphgnt.txt
pysblgnt/sblgnt/63-Lk-morphgnt.txt
pysblgnt/sblgnt/64-Jn-morphgnt.txt
pysblgnt/sblgnt/65-Ac-morphgnt.txt
pysblgnt/sblgnt/66-Ro-morphgnt.txt
pysblgnt/sblgnt/67-1Co-morphgnt.txt
pysblgnt/sblgnt/68-2Co-morphgnt.txt
pysblgnt/sblgnt/69-Ga-morphgnt.txt
pysblgnt/sblgnt/70-Eph-morphgnt.txt
pysblgnt/sblgnt/71-Php-morphgnt.txt
pysblgnt/sblgnt/72-Col-morphgnt.txt
pysblgnt/sblgnt/73-1Th-morphgnt.txt
pysblgnt/sblgnt/74-2Th-morphgnt.txt
pysblgnt/sblgnt/75-1Ti-morphgnt.txt
pysblgnt/sblgnt/76-2Ti-morphgnt.txt
pysblgnt/sblgnt/77-Tit-morphgnt.txt
pysblgnt/sblgnt/78-Phm-morphgnt.txt
pysblgnt/sblgnt/79-Heb-morphgnt.txt
pysblgnt/sblgnt/80-Jas-morphgnt.txt
pysblgnt/sblgnt/81-1Pe-morphgnt.txt
pysblgnt/sblgnt/82-2Pe-morphgnt.txt
pysblgnt/sblgnt/83-1Jn-morphgnt.txt
pysblgnt/sblgnt/84-2Jn-morphgnt.txt
pysblgnt/sblgnt/85-3Jn-morphgnt.txt
pysblgnt/sblgnt/86-Jud-morphgnt.txt
pysblgnt/sblgnt/87-Re-morphgnt.txt