Metadata-Version: 1.0
Name: py-sblgnt
Version: 0.5
Summary: pip-installable MorphGNT/SBLGNT with Python API
Home-page: http://https://github.com/morphgnt/py-sblgnt
Author: James Tauber
Author-email: jtauber@jtauber.com
License: MIT
Platform: UNKNOWN
